ad_physics-2.6.3.dist-info/top_level.txt
ad_physics-2.6.3.dist-info/WHEEL
ad_physics-2.6.3.dist-info/METADATA
ad_physics-2.6.3.dist-info/RECORD
ad_physics/__init__.py
ad_physics/ad_physics_python38.so
ad_physics.libs/libad_physics-8a865103.so
ad_physics.libs/libboost_python38-da775586.so.1.72.0
