Metadata-Version: 2.1
Name: ad-physics
Version: 2.6.3
Summary: python binding of the C++ library for Automated Driving physics data types
Home-page: https://ad-map-access.readthedocs.io/en/latest/
Author: CARLA Simulator Team
Author-email: carla.simulator@gmail.com
License: MIT
Platform: UNKNOWN
Classifier: Programming Language :: Python :: 3
Classifier: License :: OSI Approved :: MIT License
Classifier: Operating System :: OS Independent
